wallet_lib/__init__.py
wallet_lib/__main__.py
wallet_lib/bch_wallet.py
wallet_lib/btc_wallet.py
wallet_lib/dash_wallet.py
wallet_lib/wallet_base.py
wallet_lib/wallet_exceptions.py
wallet_lib/wallet_factory.py
wallet_lib/zec_wallet.py
wallet_lib/zmq_notifier.py
wallet_lib/adapters/__init__.py
wallet_lib/adapters/cmd_adapter.py
wallet_lib/adapters/rpc_adapter.py
wallet_lib/adapters/wallet_adapter_base.py
wallet_lib-1.2.7.dist-info/LICENSE
wallet_lib-1.2.7.dist-info/METADATA
wallet_lib-1.2.7.dist-info/WHEEL
wallet_lib-1.2.7.dist-info/top_level.txt
wallet_lib-1.2.7.dist-info/RECORD
