Metadata-Version: 2.1
Name: wallet-lib
Version: 1.2.7
Summary: Package to work with hot wallet for different cryptocurrency
Home-page: https://github.com/Bitcoin-com/wallet_lib
Author: Bitcoin.com
Author-email: gamesbot@bitcoin.com
License: UNKNOWN
Platform: UNKNOWN
Classifier: Programming Language :: Python :: 3
Classifier: License :: OSI Approved :: MIT License
Classifier: Operating System :: OS Independent
Requires-Python: >=3.6
Requires-Dist: pyzmq (==18.1.1)
Requires-Dist: simplejson (==3.17.0)
Requires-Dist: python-bitcoinrpc (==1.0)
